aiodantic/__init__.py
aiodantic/__main__.py
aiodantic/cli.py
aiodantic/docs.py
aiodantic/functions.py
aiodantic/helpers.py
aiodantic/json.py
aiodantic/main.py
aiodantic/openai.py
aiodantic/schema.py
aiodantic/server.py
aiodantic/service.py
aiodantic/typedef.py
aiodantic/utils.py
aiodantic-0.0.2.dist-info/METADATA
aiodantic-0.0.2.dist-info/WHEEL
aiodantic-0.0.2.dist-info/entry_points.txt
aiodantic-0.0.2.dist-info/RECORD
